tactile_patterns_for_laser_cutter/__init__.py
tactile_patterns_for_laser_cutter/data_format.py
tactile_patterns_for_laser_cutter/empty.py
tactile_patterns_for_laser_cutter/raster_noise.py
tactile_patterns_for_laser_cutter/raster_noise_islandified_bumps.py
tactile_patterns_for_laser_cutter/raster_noise_regular_bumpy_smooth_circles.py
tactile_patterns_for_laser_cutter/raster_noise_test_shape_simple_gradient.py
tactile_patterns-0.0.1.dist-info/METADATA
tactile_patterns-0.0.1.dist-info/WHEEL
tactile_patterns-0.0.1.dist-info/top_level.txt
tactile_patterns-0.0.1.dist-info/RECORD
