Metadata-Version: 2.1
Name: tactile-patterns
Version: 0.0.1
Summary: Generates patterns recognisable by touch, for use in laser-cut materials (for people who are blind or with a poor eyesight, in dark)
Home-page: https://github.com/matkoniecz/tactile_patterns
Author: Mateusz Konieczny
Author-email: matkoniecz@gmail.com
License: UNKNOWN
Platform: UNKNOWN
Classifier: Programming Language :: Python :: 3
Classifier: License :: OSI Approved :: MIT License
Classifier: Operating System :: OS Independent
Requires-Dist: jsbeautifier (<2.0,>=1.13.5)
Requires-Dist: numpy (<2.0,>=1.19.5)
Requires-Dist: pillow (<9.0,>=8.1.2)
Requires-Dist: pyproj (<3.0,>=2.5.0)
